bouncerscript/__init__.py
bouncerscript/constants.py
bouncerscript/script.py
bouncerscript/task.py
bouncerscript/utils.py
bouncerscript/data/bouncer_aliases_task_schema.json
bouncerscript/data/bouncer_locations_task_schema.json
bouncerscript/data/bouncer_submission_task_schema.json
bouncerscript/test/__init__.py
bouncerscript/test/test_script.py
bouncerscript/test/test_task.py
bouncerscript/test/test_utils.py
bouncerscript-3.6.2.dist-info/LICENSE
bouncerscript-3.6.2.dist-info/METADATA
bouncerscript-3.6.2.dist-info/WHEEL
bouncerscript-3.6.2.dist-info/entry_points.txt
bouncerscript-3.6.2.dist-info/top_level.txt
bouncerscript-3.6.2.dist-info/RECORD
